oauth2flow.py
oauth2flow-0.1.2.dist-info/METADATA
oauth2flow-0.1.2.dist-info/WHEEL
oauth2flow-0.1.2.dist-info/top_level.txt
oauth2flow-0.1.2.dist-info/RECORD
