Metadata-Version: 2.2
Name: oauth2flow
Version: 0.1.2
Summary: Client Authenticator for OAuth2
Author-email: Paulo Alexandre <paulo.alexandre@tjdft.jus.br>
License: MIT License
Classifier: Intended Audience :: Developers
Classifier: License :: OSI Approved :: MIT License
Classifier: Programming Language :: Python :: 3.12
Requires-Python: >=3.12
Requires-Dist: requests<3.0.0,>=2.23.0
Requires-Dist: attrs<25.0.0,>=24.3.0
